secure_token/__init__.py
secure_token/cli.py
secure_token/config.py
secure_token/exceptions.py
secure_token/token_manager.py
secure_token/utils.py
secure_token/validators.py
secure_token-1.0.2.dist-info/licenses/LICENSE
secure_token-1.0.2.dist-info/METADATA
secure_token-1.0.2.dist-info/WHEEL
secure_token-1.0.2.dist-info/entry_points.txt
secure_token-1.0.2.dist-info/top_level.txt
secure_token-1.0.2.dist-info/RECORD
