Metadata-Version: 2.4
Name: secure-token
Version: 1.0.2
Summary: Secure Token System for Python
Author-email: AmirHossein Babaee <amirhoosenbabai82@gmail.com>
Maintainer-email: AmirHossein Babaee <amirhoosenbabai82@gmail.com>
License: MIT
Project-URL: Homepage, https://github.com/amirhosein2004/secure-token
Project-URL: Documentation, https://secure-token.readthedocs.io
Project-URL: Repository, https://github.com/amirhosein2004/secure-token.git
Project-URL: Bug Tracker, https://github.com/amirhosein2004/secure-token/issues
Project-URL: Changelog, https://github.com/amirhosein2004/secure-token/blob/main/CHANGELOG.md
Keywords: security,token,authentication,encryption,jwt-alternative
Classifier: Development Status :: 4 - Beta
Classifier: Intended Audience :: Developers
Classifier: License :: OSI Approved :: MIT License
Classifier: Operating System :: OS Independent
Classifier: Programming Language :: Python :: 3
Classifier: Programming Language :: Python :: 3.8
Classifier: Programming Language :: Python :: 3.9
Classifier: Programming Language :: Python :: 3.10
Classifier: Programming Language :: Python :: 3.11
Classifier: Programming Language :: Python :: 3.12
Classifier: Topic :: Security :: Cryptography
Classifier: Topic :: Software Development :: Libraries :: Python Modules
Classifier: Topic :: Internet :: WWW/HTTP :: Session
Classifier: Typing :: Typed
Requires-Python: >=3.8
License-File: LICENSE
Requires-Dist: cryptography>=41.0.0
Requires-Dist: pydantic-settings>=2.0.0
Provides-Extra: dev
Requires-Dist: pytest==8.4.1; extra == "dev"
Requires-Dist: pytest-cov==6.2.1; extra == "dev"
Requires-Dist: black>=23.0.0; extra == "dev"
Requires-Dist: isort>=5.12.0; extra == "dev"
Requires-Dist: flake8>=6.0.0; extra == "dev"
Requires-Dist: mypy>=1.5.0; extra == "dev"
Requires-Dist: pre-commit==4.3.0; extra == "dev"
Requires-Dist: bandit>=1.7.5; extra == "dev"
Requires-Dist: safety>=2.3.0; extra == "dev"
Provides-Extra: test
Requires-Dist: pytest==8.4.1; extra == "test"
Requires-Dist: pytest-cov==6.2.1; extra == "test"
Dynamic: license-file
